burpr/__init__.py
burpr/burpr.py
burpr/enums/ProtocolEnum.py
burpr/enums/TransportEnum.py
burpr/enums/__init__.py
burpr/models/BurpRequest.py
burpr/models/__init__.py
tests/__init__.py
tests/test_burpr.py
burpr-0.3.0.dist-info/LICENSE.txt
burpr-0.3.0.dist-info/METADATA
burpr-0.3.0.dist-info/WHEEL
burpr-0.3.0.dist-info/top_level.txt
burpr-0.3.0.dist-info/RECORD
