Metadata-Version: 2.1
Name: burpr
Version: 0.3.0
Summary: A Burp Suite request parser, used for aid in assessing application security functionality.
Home-page: https://github.com/krystianbajno/burpr
Author: Krystian Bajno
Author-email: krystian.bajno@gmail.com
License: MIT
Keywords: burp suite burpsuite request parser security testing http http2
Classifier: Programming Language :: Python :: 3
Classifier: Programming Language :: Python :: 3.7
Classifier: Programming Language :: Python :: 3.8
Classifier: Programming Language :: Python :: 3.9
Classifier: Programming Language :: Python :: 3.10
Classifier: Programming Language :: Python :: 3.11
Classifier: Programming Language :: Python :: 3.12
Classifier: License :: OSI Approved :: MIT License
Classifier: Operating System :: OS Independent
Classifier: Intended Audience :: Developers
Classifier: Intended Audience :: Information Technology
Classifier: Topic :: Security
Classifier: Topic :: Software Development :: Libraries :: Python Modules
Requires-Python: >=3.7
Requires-Dist: requests>=2.25.0
Requires-Dist: httpx[http2]>=0.23.0
Provides-Extra: dev
Requires-Dist: pytest>=7.0.0; extra == "dev"
Requires-Dist: pytest-cov; extra == "dev"
